{
  "id": 999,
  "name": "Monster Slayer",
  "mtype": "secondary",
  "ruleset": 1,
  "options": [
    {
      "name": "",
      "description": "",
      "location": "1",
      "data": ""
    },
    {  
      "name": "Action : Valut",
      "description": "Jump + Attack w/ Polearm. Move at least 3 units, +1 bonus dice.",
      "location": "2a",
      "data": "XINE=1"
    },
    {
      "name": "",
      "description": "",
      "location": "2b",
      "data": ""
    },
    {
      "name": "",
      "description": "",
      "location": "3",
      "data": ""
    },
    {
      "name": "Monster Tamer",
      "description": "Gain +1 skill with wildcraft. Your taming skill also works on monsters.",
      "location": "4a",
      "data": ""
    },
    {
      "name": "Heavy Weaponry",
      "description": "Gain +1 skill with complex melee weapons.",
      "location": "4b",
      "data": ""
    },
    {
      "name": "",
      "description": "Gain +1 skill with deflection. Gain a bonus dice on defense checks against huge and larger creatures.",
      "location": "5",
      "data": ""
    },
    {
      "name": "",
      "description": "",
      "location": "6a",
      "data": ""
    },
    {
      "name": "",
      "description": "",
      "location": "6b",
      "data": ""
    },
    {
      "name": "",
      "description": "",
      "location": "7",
      "data": ""
    }
  ]
}