{
  "name": "Crossbow",
  "description": "A mechanical bow mounted on a stock that shoots bolts. Its mechanical advantage makes it easier to use than a traditional bow, allowing even untrained users to be effective.",
  "type": "weapon",
  "weapon_category": "simpleRanged",
  "hands": 2,
  "weight": 2,
  "value": 1300,
  "bonus_attack": 0,
  "rarity": "common",
  "primary": {
    "damage": "7",
    "damage_extra": "1",
    "damage_type": "physical",
    "category": "ranged",
    "energy": 0,
    "secondary_damage": 0,
    "secondary_damage_extra": 0,
    "secondary_damage_type": "none",
    "min_range": 2,
    "max_range": 4
  },
  "health": {
    "max": 0,
    "recovery": 0
  },
  "energy": {
    "max": 0,
    "recovery": 0
  },
  "resolve": {
    "max": 0,
    "recovery": 0
  },
  "movement": 0,
  "attributes": {},
  "basic": {},
  "weapon": {},
  "magic": {},
  "craft": {},
  "mitigation": {},
  "detections": {},
  "immunities": {},
  "recipe": {
    "type": "engineering",
    "difficulty": 6,
    "ingredients": [
      "Release Mechanism",
      "Light Limbs",
      "Bowstring",
      "Bindings"
    ]
  },
  "encumbrance_penalty": 0,
  "foundry_icon": "icons/weapons/crossbows/crossbow-blue.webp",
  "foundry_id": "qg4j0wjgxyzgt5mg"
}
