{
  "id": 105,
  "name": "Melee Specialist",
  "mtype": "core",
  "ruleset": 1,
  "options": [
    {
      "name": "Fledgling Combatant",
      "description": "You have trained with several types of melee weapons. Gain +1 skill with simple and complex melee weapons.",
      "location": "1",
      "data": "WS3=1:WS5=1"
    },
    {
      "name": "Action : Power Strike",
      "description": "You make a powerful attack against an enemy with a simple or complex melee weapon that consumes a lot of energy, adding 2 might dice to your weapon attack. These dice are not eligible for critical hits.",
      "location": "2a",
      "data": "XINE=2"
    },
    {
      "name": "Action : Close the Gap",
      "description": "You move up to 2 units towards an enemy and then make an attack against them with a melee weapon.",
      "location": "2b",
      "data": "XINE=1"
    },
    {
      "name": "Reaction : Reactive Strike",
      "description": "When an enemy moves within your melee range, make an attack against them with a simple or complex melee weapon.",
      "location": "3",
      "data": "ZINE=1"
    },
    {
      "name": "Conditioning",
      "description": "Your dedication to weapon training has resulted in increased conditioning. You gain +1 skill with fitness and +2 maximum health.",
      "location": "4a",
      "data": "SSA=1:A1=2"
    },
    {
      "name": "Parry",
      "description": "You have trained to block attacks with your weapons. You gain +1 skill with deflection.",
      "location": "4b",
      "data": "SSB=1"
    },
    {
      "name": "Skilled Combatant",
      "description": "You have trained with several types of melee weapons. Gain +1 skill with simple and complex melee weapons.",
      "location": "5",
      "data": "WS3=1:WS5=1"
    },
    {
      "name": "Perfect Form",
      "description": "",
      "location": "6a",
      "data": "SSG=1:TG"
    },
    {
      "name": "Brutal Criticals",
      "description": "When you score any number of critical hits on a simple or complex melee weapon attack, add 5 damage to the final calculation.",
      "location": "6b",
      "data": "TG"
    },
    {
      "name": "Talented Combatant",
      "description": "Your relentless training has resulted in +1 talent with simple and complex melee weapons.",
      "location": "7",
      "data": "WT3=1:WT5=1"
    }
  ]
}