{
  "id": 105,
  "name": "Outsider",
  "mtype": "personality",
  "ruleset": 1,
  "stressors":["You become imprisoned against your will","You face public mockery or accusation","Your core beliefs face challenge"],
 "options": [
      {
      "name": "Outsider",
      "description": "You are an outsider, never quite fitting in with established social groups and viewing societies from a perspective that others cannot share. Your position on the margins grants you unique insights and adaptability, though it often leaves you searching for acceptance or purpose. You value independence, authenticity, and adaptability above all else.",
      "mtype": "core",
      "location": "1",
      "cost": 2,
      "data": "AE=1"
    },
   
    {
      "name": "Chameleon",
      "description": "You have skill with masking the fact that you are an outsider and can often hide yourself in plain sight. Gain +1 to your stealth skill. When rolling a stealth check as part of a group, your stealth check becomes equal to the highest roll of the group.",
      "mtype": "core",
      "location": "2a",
      "cost": 2,
      "data": ""
    },
    {
      "name": "Polyglot",
      "description": "You pick up the local language quickly and make an effort to adapt to local customs. Gain +1 skill with persuasion. Additionally, gain +2 language points.",
      "mtype": "core",
      "location": "2b",
      "cost": 2,
      "data": ""
    },
    {
      "name": "Downtime Action : Vanish",
      "description": "You take some time and scrub any existence or record of your existence in an area, the size of which is determined by a persuasion check; A check of an 6-9 is midly successful and allows you to convince those within a small area like a village or city block, while a 10 or higher is very successful and expands over a large town. On a perfect check, your effort is wide spread and can expand over a larg city.",
      "mtype": "core",
      "location": "3",
      "cost": 2,
      "data": ""
    },
    {
      "name": "Action : Slip Away",
      "description": "You slip away from combat or a social situation if you are at least a short distance (10 units) away from the nearest enemy and are within 2 units of an object or creature that grants you at least half-cover.",
      "mtype": "core",
      "location": "4a",
      "cost": 2,
      "data": "XX"
    },
    {
      "name": "Reaction : Adapt",
      "description": "In response to taking damage of the same type you've already taken since the end of your last turn, gain 1d6 mitigation to that type before calculating damage.",
      "mtype": "core",
      "location": "4b",
      "cost": 2,
      "data": "ZX"
    },
    {
      "name": "WIP",
      "description": "This is currently not implemented",
      "mtype": "core",
      "location": "5",
      "cost": 2,
      "data": ""
    },
    {
      "name": "WIP",
      "description": "This is currently not implemented",
      "mtype": "core",
      "location": "6a",
      "cost": 2,
      "data": ""
    },
    {
      "name": "WIP",
      "description": "This is currently not implemented",
      "mtype": "core",
      "location": "6b",
      "cost": 2,
      "data": ""
    },
    {
      "name": "Sovereign Stranger",
      "description": "Gain +1 talent with social and +1 skill with insight.",
      "mtype": "core",
      "location": "7",
      "cost": 3,
      "data": "ST5=1:SSS=1"
    }
  ]
}
