{
  "id": 12,
  "name": "Ekshaan",
  "description": "Vermin of the Depths\nThe Ekshaan are a kobold culture built upon banding together and being fearless despite their small stature. They dwell underground, perfecting traps and tactics to overcome larger foes.",
  "options": [
    {
      "name": "Skitterstrike",
      "description": "You move up to Half your Movement Speed. For every Creature you come within 1 Unit of, you can make an Attack with a Light or Unarmed Weapon.",
      "data": "XX3"
    },
    {
      "name": "Kobold Diplomacy",
      "description": "Gain +1 Persuasion and you can communicate basic concepts through gestures with any intelligent creature.",
      "data": "AST=1"
    },
    {
      "name": "Trap Expertise",
      "description": "Gain +1 Thievery and you can detect traps without actively searching for them.",
      "data": "ASH=1"
    }
  ]
}